sostore/__init__.py
sostore/errors.py
sostore/collection.py
sostore-0.7.dist-info/metadata.json
sostore-0.7.dist-info/WHEEL
sostore-0.7.dist-info/METADATA
sostore-0.7.dist-info/DESCRIPTION.rst
sostore-0.7.dist-info/top_level.txt
sostore-0.7.dist-info/RECORD
