Metadata-Version: 2.0
Name: sostore
Version: 0.7
Summary: SQLite Object Store - An absurdly simple object "database" for Python
Home-page: https://bitbucket.org/ArmstrongJ/sostore/overview
Author: Jeffrey Armstrong
Author-email: jeffrey.armstrong@approximatrix.com
License: GPL3
Platform: UNKNOWN
Classifier: Topic :: Database
Classifier: Development Status :: 4 - Beta
Classifier: Intended Audience :: Developers
Classifier: License :: OSI Approved :: GNU General Public License v3 or later (GPLv3+)
Classifier: Operating System :: OS Independent
Classifier: Programming Language :: Python :: 2.6
Classifier: Programming Language :: Python :: 2.7
Classifier: Programming Language :: Python :: 3
